django_liquid/__init__.py
django_liquid/liquid.py
django_liquid-1.1.0.dist-info/LICENSE
django_liquid-1.1.0.dist-info/LICENSE.django
django_liquid-1.1.0.dist-info/METADATA
django_liquid-1.1.0.dist-info/WHEEL
django_liquid-1.1.0.dist-info/top_level.txt
django_liquid-1.1.0.dist-info/RECORD
