Metadata-Version: 2.1
Name: django-liquid
Version: 1.1.0
Summary: A Django template backend for Liquid.
Home-page: https://github.com/jg-rp/django-liquid
License: BSD-3-Clause
Project-URL: Documentation, https://jg-rp.github.io/liquid/guides/django-liquid
Project-URL: Issue Tracker, https://github.com/jg-rp/django-liquid/issues
Project-URL: Source Code, https://github.com/jg-rp/django-liquid
Project-URL: Change Log, https://github.com/jg-rp/django-liquid/blob/main/CHANGES.rst
Classifier: Development Status :: 5 - Production/Stable
Classifier: Intended Audience :: Developers
Classifier: License :: OSI Approved :: MIT License
Classifier: Programming Language :: Python :: 3
Classifier: Programming Language :: Python :: 3.7
Classifier: Programming Language :: Python :: 3.8
Classifier: Programming Language :: Python :: 3.9
Classifier: Programming Language :: Python :: 3.10
Classifier: Programming Language :: Python :: 3.11
Classifier: Programming Language :: Python :: Implementation :: CPython
Requires-Python: >=3.7
License-File: LICENSE
License-File: LICENSE.django
Requires-Dist: django (>=3.2)
Requires-Dist: python-liquid[autoescape] (>=0.7.4)
